openimis_be_report-1.7.0.dist-info/licenses/LICENSE.md
report/__init__.py
report/admin.py
report/apps.py
report/default_report.py
report/models.py
report/schema.py
report/services.py
report/tests.py
report/urls.py
report/views.py
report/migrations/0001_initial.py
report/migrations/0002_auto_20220308_1414.py
report/migrations/0003_update_permissions.py
report/migrations/0004_generatedreports.py
report/migrations/0005_add_report_right_to_EO.py
report/migrations/0006_version_report_def.py
report/migrations/0007_add_edit_perms_imis_and_scheme_admin.py
report/migrations/0008_add_missing_fields_to_django_scheme.py
report/migrations/0009_set_managed_to_true.py
report/migrations/0010_add_query_rights.py
report/migrations/__init__.py
report/static/report/reportbro/reportbro.css
report/static/report/reportbro/reportbro.css.map
report/static/report/reportbro/reportbro.js
report/static/report/reportbro/reportbro.js.LICENSE.txt
report/static/report/reportbro/reportbro.js.map
report/static/report/reportbro/reportbro.min.js
report/static/report/reportbro/reportbro.min.js.map
report/static/report/reportbro/ext/jquery.js
report/static/report/reportbro/ext/jquery.js.LICENSE.txt
report/static/report/reportbro/fonts/DejaVuSans-Bold.ttf
report/static/report/reportbro/fonts/DejaVuSans-BoldOblique.ttf
report/static/report/reportbro/fonts/DejaVuSans-Oblique.ttf
report/static/report/reportbro/fonts/DejaVuSans.ttf
report/static/report/reportbro/fonts/FreeSans.ttf
report/static/report/reportbro/fonts/FreeSansBold.ttf
report/static/report/reportbro/fonts/FreeSansBoldOblique.ttf
report/static/report/reportbro/fonts/FreeSansOblique.ttf
report/static/report/reportbro/fonts/NotoNaskhArabic.ttf
report/static/report/reportbro/fonts/NotoSans-Bold.ttf
report/static/report/reportbro/fonts/NotoSans-BoldItalic.ttf
report/static/report/reportbro/fonts/NotoSans-Italic.ttf
report/static/report/reportbro/fonts/NotoSans-Regular.ttf
report/static/report/reportbro/fonts/NotoSansArabic.ttf
report/static/report/reportbro/fonts/NotoSansEthiopic.ttf
openimis_be_report-1.7.0.dist-info/METADATA
openimis_be_report-1.7.0.dist-info/WHEEL
openimis_be_report-1.7.0.dist-info/top_level.txt
openimis_be_report-1.7.0.dist-info/RECORD
