Metadata-Version: 2.4
Name: openimis-be-report
Version: 1.7.0
Summary: The openIMIS Report reference module.
Home-page: https://openimis.org/
Author: Xavier Gillmann
Author-email: xgillmann@bluesquarehub.com
License: GNU AGPL v3
Classifier: Environment :: Web Environment
Classifier: Framework :: Django
Classifier: Framework :: Django :: 3.1
Classifier: Intended Audience :: Developers
Classifier: License :: OSI Approved :: GNU Affero General Public License v3
Classifier: Operating System :: OS Independent
Classifier: Programming Language :: Python
Classifier: Programming Language :: Python :: 3.8
Classifier: Programming Language :: Python :: 3.9
License-File: LICENSE.md
Requires-Dist: django
Requires-Dist: django-db-signals
Requires-Dist: djangorestframework
Requires-Dist: cached-property
Requires-Dist: nepalicalendar
Requires-Dist: openimis-be-core
Requires-Dist: reportbro-lib
Requires-Dist: reportbro-fpdf
Dynamic: author
Dynamic: author-email
Dynamic: classifier
Dynamic: home-page
Dynamic: license
Dynamic: license-file
Dynamic: requires-dist
Dynamic: summary
